Metadata-Version: 1.2
Name: shogun
Version: 0.0.2
Summary: Opinionated Typed Configuration
Home-page: https://github.com/menpo/shogun
Author: The Menpo Team
Author-email: hello@menpo.org
License: UNKNOWN
Platform: UNKNOWN
Classifier: Programming Language :: Python :: 3
Classifier: License :: OSI Approved :: BSD License
Classifier: Operating System :: OS Independent
Requires-Python: >=3.6
